aiohttp_but_its_requests/__init__.py
aiohttp_but_its_requests/aiohttp_but_its_requests.py
aiohttp_but_its_requests-0.1.0.dist-info/LICENSE
aiohttp_but_its_requests-0.1.0.dist-info/METADATA
aiohttp_but_its_requests-0.1.0.dist-info/WHEEL
aiohttp_but_its_requests-0.1.0.dist-info/top_level.txt
aiohttp_but_its_requests-0.1.0.dist-info/RECORD
