Metadata-Version: 2.1
Name: aiohttp-but-its-requests
Version: 0.1.0
Summary: The speed of aiohttp simplified to the level of requests.
Home-page: UNKNOWN
Author: TriC
License: UNKNOWN
Keywords: aiohttp,requests,fast
Platform: UNKNOWN
Classifier: Programming Language :: Python :: 3
Classifier: License :: OSI Approved :: MIT License
Classifier: Operating System :: OS Independent
Requires-Python: >= 3.6
Requires-Dist: aiohttp
Requires-Dist: nest-asyncio
